[
  {
    "ID": 1,
    "CPF": "00347355773",
    "PRESTADORES": "AGNUS AMANCIO PANTALEAO",
    "Contato": 27998488819,
    "E-mail": "agnuspantaleao@hotmail.com",
    "CEP": 29066310,
    "Endereco ": "Avenida Adalberto Simao Nader",
    "Numero": 565,
    "Bairro": "Mata da Praia"
  },
  {
    "ID": 2,
    "CPF": "97951013749",
    "PRESTADORES": "ANA CLAUDIA FERRARI",
    "Contato": 27999619572,
    "E-mail": "dra.anacferrari@gmail.com",
    "CEP": 29070170,
    "Endereco ": "Avenida Rozendo Serapiao de Souza Filho",
    "Numero": 630,
    "Complemento": "sala 06",
    "Bairro": "Republica"
  },
  {
    "ID": 3,
    "CPF": "74095544600",
    "PRESTADORES": "ANDRE LUIZ DE ABREU",
    "Contato": 27993112923,
    "E-mail": "abreuand@hotmail.com",
    "CEP": 29101350,
    "Endereco ": "Rua Construtor Sebastiao Soares de Souza",
    "Numero": 501,
    "Bairro": "Praia da Costa"
  },
  {
    "ID": 4,
    "CPF": "49127888215",
    "PRESTADORES": "ANDREIA FERRAZ DE CASTRO DIAS",
    "Contato": 27998827114,
    "E-mail": "andreiaferraz01@gmail.com",
    "CEP": 29165680,
    "Endereco ": "Avenida Eldes Scherrer Souza",
    "Numero": 26,
    "Complemento": "sala 205",
    "Bairro": "Parque Residencial Laranjeiras"
  },
  {
    "ID": 5,
    "CPF": "08347483710",
    "PRESTADORES": "ARISTEO ATSUSHI TAKASAKI",
    "Contato": 27999989633,
    "E-mail": "smiletakasaki@gmail.com",
    "CEP": 29060200,
    "Endereco ": "Praca Regina Frigeri Furno",
    "Numero": 120,
    "Complemento": "ponto referencia pracinha do supermercado bh",
    "Bairro": "Jardim da Penha"
  },
  {
    "ID": 6,
    "CPF": "08635949722",
    "PRESTADORES": "ARTHUR FONSECA",
    "Contato": 27999480057,
    "E-mail": "dr.arthurfo@hotmail.com",
    "CEP": 29092110,
    "Endereco ": "Rua Carlos Lindenberg",
    "Numero": 94,
    "Complemento": "apto 319",
    "Bairro": "Jardim Camburi"
  },
  {
    "ID": 7,
    "CPF": "13619645701",
    "PRESTADORES": "ARTHUR MIRANDA LYRA",
    "Contato": 27992479976,
    "E-mail": "salyinstituto@gmail.com",
    "CEP": 29101350,
    "Endereco ": "Rua Construtor Sebastiao Soares de Souza",
    "Numero": 40,
    "Complemento": "sala 1004, ed Infinity Center",
    "Bairro": "Praia da costa, Vila Velha"
  },
  {
    "ID": 8,
    "CPF": "08485451767",
    "PRESTADORES": "BRUNO DA COSTA DEKACHE",
    "Contato": 27999433527,
    "E-mail": "Bdekache@hotmail.com",
    "CEP": 29056243,
    "Endereco ": "Avenida Nossa Senhora da Penha",
    "Numero": 1495,
    "Complemento": "Ed coorporate Center, Sala 115 - Em frente a Petrobras",
    "Bairro": "Santa Lucia, Vit\u00F3ria"
  },
  {
    "ID": 9,
    "CPF": "08642223782",
    "PRESTADORES": "BRUNO SILVA FONSECA",
    "Contato": 27999719882,
    "E-mail": "coepraiadocanto@gmail.com",
    "CEP": 29055620,
    "Endereco ": "Rua Joao da Cruz",
    "Numero": 480,
    "Bairro": "Praia do Canto"
  },
  {
    "ID": 10,
    "CPF": "79261230725",
    "PRESTADORES": "CARLOS ROBERTO DE ANGELO",
    "Contato": 27995265880,
    "E-mail": "carlosrobertodeangelo@gmail.com",
    "CEP": 29056230,
    "Endereco ": "Rua Misael Pedreira da Silva",
    "Numero": 70,
    "Complemento": "sala 506",
    "Bairro": "Santa Lucia, Vit\u00F3ria"
  },
  {
    "ID": 11,
    "CPF": "03152512716",
    "PRESTADORES": "CASSIO LEITE",
    "Contato": 27988377995,
    "E-mail": "dr.cassioleitebarros@gmail.com",
    "CEP": 29060130,
    "Endereco ": "Rua Eugenilio Ramos",
    "Numero": 580,
    "Bairro": "Jardim da Penha"
  },
  {
    "ID": 12,
    "CPF": "02646399600",
    "PRESTADORES": "CID VIEIRA DE OLIVEIRA DAMIAO",
    "Contato": 27998002424,
    "Contato 2": 27999719169,
    "E-mail": "vieira.cid@gmail.com",
    "CEP": 29066040,
    "Endereco ": "Avenida Carlos Gomes de Sa",
    "Numero": 730,
    "Bairro": "Mata da Praia"
  },
  {
    "ID": 13,
    "CPF": "90749154691",
    "CNPJ": "07254943000190",
    "PRESTADORES": "CRISTIANA PEREIRA GUEDES",
    "Contato": 27996989099,
    "E-mail": "clinicacristianaguedes@gmail.com",
    "CEP": 29050335,
    "Endereco ": "Avenida Nossa Senhora dos Navegantes",
    "Numero": 451,
    "Bairro": "Enseada do Sua"
  },
  {
    "ID": 14,
    "CPF": "03142456775",
    "PRESTADORES": "CRISTIANI PACHECO DE OLIVEIRA",
    "Contato": 27999813001,
    "Contato 2": 27992944105,
    "E-mail": "dracristiani@gmail.com",
    "CEP": 29109310,
    "Endereco ": "Rua Carlos Almeida",
    "Numero": 5454,
    "Bairro": "Santos Dumont"
  },
  {
    "ID": 15,
    "CPF": "01728684757",
    "PRESTADORES": "DEUSIANY CUZZOUL",
    "Contato": 27999848064,
    "E-mail": "dra.deusiany@hotmail.com",
    "CEP": 29190920,
    "Endereco ": "Rua Jose Alves da Costa",
    "Numero": 56,
    "Bairro": "centro"
  },
  {
    "ID": 16,
    "CPF": "11686568770",
    "PRESTADORES": "DIANA BANDEIRA DIAS DE MEDEIROS",
    "Contato": 27999052020,
    "E-mail": "dianabdias@yahoo.com.br",
    "CEP": 29050545,
    "Endereco ": "Rua Jose Alexandre Buaiz",
    "Numero": 160,
    "Complemento": "Edificio London Office Tower, salas 904 a 906",
    "Bairro": "Enseada do Sua"
  },
  {
    "ID": 17,
    "PRESTADORES": "EDISON MEDICI BRUM COSTA",
    "Contato": 27988061286
  },
  {
    "ID": 18,
    "CPF": "91838207791",
    "PRESTADORES": "EDMILSON GONCALVES VIEIRA",
    "Contato": 27998424005,
    "E-mail": "edmilsongoncalvesvieira@gmail.com",
    "CEP": 29136013,
    "Endereco ": "Rua Santa Helena",
    "Numero": 103,
    "Bairro": "Vila Bethania- Viana"
  },
  {
    "ID": 19,
    "CPF": "01369845766",
    "PRESTADORES": "EDSON VANDER BARBOSA SEGAL",
    "Contato": 27988611172,
    "E-mail": "segala.segal@gmail.com",
    "CEP": 29200430,
    "Endereco ": "Avenida Davino Mattos",
    "Numero": 55,
    "Complemento": "sala 108",
    "Bairro": "Centro"
  },
  {
    "ID": 20,
    "CPF": "03588202781",
    "PRESTADORES": "EDUARDO ANTONIO EMERICH GOMES",
    "Contato": 27981260052,
    "E-mail": "inovilabvix@gmail.com",
    "CEP": 29101410,
    "Endereco ": "Avenida Champagnat",
    "Numero": 304,
    "Bairro": "Praia da Costa"
  },
  {
    "ID": 21,
    "CPF": "07880858679",
    "PRESTADORES": "EDUARDO FERNANDES OLIVEIRA",
    "Contato": 27999705358,
    "E-mail": "maiarasilva180123@gmail.com",
    "CEP": 29100011,
    "Endereco ": "Avenida Champagnat",
    "Numero": 717,
    "Complemento": "sala 104",
    "Bairro": "Centro de Vila Velha"
  },
  {
    "ID": 22,
    "CPF": "07675412788",
    "PRESTADORES": "FABIANO SILVA FONSECA",
    "Contato": 27995785295,
    "E-mail": "fonseca.fabiano@uol.com.br",
    "CEP": 29050545,
    "Endereco ": "Rua Jose Alexandre Buaiz",
    "Numero": 190,
    "Complemento": "Edificio Master tower, 12 andar",
    "Bairro": "Enseada do Sua"
  },
  {
    "ID": 23,
    "PRESTADORES": "FABIO ALEXANDRE MOREIRA",
    "Contato": 27999283675
  },
  {
    "ID": 24,
    "CPF": "12532095709",
    "PRESTADORES": "FABIOLA BARONE",
    "Contato": 27998033146,
    "E-mail": "drafabiolabarone@gmail.com",
    "CEP": 29090740,
    "Endereco ": "Rua Maria Auxiliadora Gomes Salomao",
    "Numero": 116,
    "Complemento": "sala 1",
    "Bairro": "Jardim Camburi, Vitoria"
  },
  {
    "ID": 25,
    "CPF": "69113718568",
    "PRESTADORES": "FABRICIO FELIPPE",
    "Contato": 27999697292,
    "Contato 2": 27996462210,
    "E-mail": "fabfelrocha@hotmail.com",
    "CEP": 29845000,
    "Endereco ": "Rua Cotaxe",
    "Numero": 527,
    "Bairro": "Boa Esperanca"
  },
  {
    "ID": 26,
    "PRESTADORES": "FELIPE BONESI ALVARENGA",
    "Contato": 27999477477,
    "E-mail": "felipebonesi@gmail.com",
    "CEP": 29045320,
    "Endereco ": "Rua Jos\u00E9 Farias",
    "Bairro": "santa Lucia, Vitoria"
  },
  {
    "ID": 27,
    "CPF": "11414414706",
    "PRESTADORES": "FELIPE MARQUES DE AGUIAR OLIVEIRA",
    "Contato": 27999291464,
    "E-mail": "felipe_maoliveira@yahoo.com.br"
  },
  {
    "ID": 28,
    "CPF": "07144764713",
    "PRESTADORES": "FERNANDA MURI LOPES BROSEGHINI",
    "Contato": 27998494769,
    "Contato 2": 2733253022,
    "E-mail": "fernandalopesmb@hotmail.com",
    "CEP": 29260000,
    "Endereco ": "Avenida Sen. Jefferson de Aguiar",
    "Numero": 83,
    "Bairro": "centro"
  },
  {
    "ID": 29,
    "PRESTADORES": "FRANCISCO POLDI JUNIOR",
    "Contato": 27999492055,
    "Contato 2": 2733253022,
    "E-mail": "atendimento@odontolarvitoria.com.br",
    "CEP": 29060120,
    "Endereco ": "Rua Carlos Eduardo Monteiro de Lemos",
    "Numero": 135,
    "Bairro": "Jardim da Penha"
  },
  {
    "ID": 30,
    "CPF": "08993575711",
    "PRESTADORES": "FRANCISCO QUINTAO MACEDO",
    "Contato": 27998193466,
    "Contato 2": 27997568362,
    "E-mail": "facescirurgiaeodontologia@gmail.com",
    "CEP": 29161001,
    "Endereco ": "Rodovia Governador Mario Covas",
    "Numero": 591,
    "Complemento": "sala 110a",
    "Bairro": "Boa Vista II"
  },
  {
    "ID": 31,
    "CPF": "92521169749",
    "PRESTADORES": "FREDERICO GUIMARAES",
    "Contato": 27999605544,
    "E-mail": "fredericobg@gmail.com",
    "CEP": 29056245,
    "Endereco ": "Avenida Nossa Senhora da Penha",
    "Numero": 699,
    "Complemento": "sala 911b",
    "Bairro": "Santa Lucia, Vit\u00F3ria"
  },
  {
    "ID": 32,
    "CPF": "15487028702",
    "PRESTADORES": "GABRIEL GOMES DE OLIVEIRA",
    "Contato": 27999672122,
    "E-mail": "adm.gamaodontologia@gmail.com",
    "CEP": 29103848,
    "Endereco ": "Rua Dylio Penedo",
    "Numero": 8,
    "Bairro": "Praia de Itaparica, Vila Velha"
  },
  {
    "ID": 33,
    "CPF": "03152378726",
    "PRESTADORES": "GEORGENES MACHADO ROSSI",
    "Contato": 27995003731,
    "E-mail": "odontogeadm@gmail.com",
    "CEP": 29066310,
    "Endereco ": "Avenida Adalberto Simao Nader",
    "Numero": 425,
    "Complemento": "sala 103",
    "Bairro": "Mata da Praia"
  },
  {
    "ID": 34,
    "CPF": "08257355720",
    "PRESTADORES": "GIANFRANCO MARQUES",
    "Contato": 27999391110,
    "E-mail": "gianfmarques@hotmail.com",
    "CEP": 29045300,
    "Endereco ": "Rua Jose Farias",
    "Numero": 98,
    "Bairro": "Santa Luiza"
  },
  {
    "ID": 35,
    "CPF": "96159723715",
    "PRESTADORES": "GILMAR DE PAULA CORTE REAL",
    "Contato": 27988114664,
    "Contato 2": 27998601232,
    "E-mail": "gilmarcorte@gmail.com",
    "CEP": 29215017,
    "Endereco ": "Rua Adolpho Cassoli",
    "Numero": 25,
    "Bairro": "Muquicaba"
  },
  {
    "ID": 36,
    "CPF": "08786517724",
    "PRESTADORES": "GISELA ARAUJO DE OLIVEIRA",
    "Contato": 27992255616,
    "Contato 2": 27992255615,
    "E-mail": "giselaprotese2@outlook.com",
    "CEP": 29055620,
    "Endereco ": "Rua Joao da Cruz",
    "Numero": 480,
    "Bairro": "Praia do Canto"
  },
  {
    "ID": 37,
    "CPF": "01328132625",
    "PRESTADORES": "HARLEI AUGUSTO BUENO ALVES",
    "Contato": 35988534725,
    "E-mail": "harleialves@hotmail.com",
    "CEP": 37800000,
    "Endereco ": "Rua Santo Antonio ",
    "Numero": 368,
    "Complemento": "sala 203 edificio comercial",
    "Bairro": "Centro"
  },
  {
    "ID": 38,
    "CPF": "12269357701",
    "PRESTADORES": "HELEN DALRIO GONCALVES",
    "Contato": 27999323953,
    "E-mail": "helendgon@gmail.com",
    "CEP": 29172105,
    "Endereco ": "Rua dos Cravos",
    "Numero": 30,
    "Complemento": "viva sorriso",
    "Bairro": "Feu Rosa"
  },
  {
    "ID": 39,
    "CPF": "10581566750",
    "PRESTADORES": "HUMBERTO GOMES",
    "Contato": 27999186822,
    "E-mail": "humbertosg91@gmail.com",
    "CEP": 29161582,
    "Endereco ": "Rua Niteroi",
    "Numero": 80,
    "Complemento": "apt 202"
  },
  {
    "ID": 40,
    "CPF": "13135279120",
    "PRESTADORES": "IRIS DE CASTRO ROSA",
    "Contato": 27981512583,
    "E-mail": "iriscastro2004@yahoo.com.br",
    "CEP": 29045402,
    "Endereco ": "Avenida Nossa Senhora da Penha",
    "Numero": 2462,
    "Bairro": "Santa Luiza"
  },
  {
    "ID": 41,
    "CPF": "12482566703",
    "PRESTADORES": "ISABELLA CASTOR ALTOE",
    "Contato": 27999499350,
    "E-mail": "castor.isabella@gmail.com",
    "CEP": 29055940,
    "Endereco ": "Avenida Nossa Senhora da Penha",
    "Numero": 570,
    "Bairro": "Praia do Canto"
  },
  {
    "ID": 42,
    "CPF": "14809050700",
    "PRESTADORES": "ISABELLA COUTINHO SILVA",
    "Contato": 27992369618,
    "E-mail": "contatoisabellacs@gmail.com",
    "CEP": 29060760,
    "Endereco ": "Rua Ronaldo Scampini",
    "Numero": 737,
    "Bairro": "Jardim da Penha"
  },
  {
    "ID": 43,
    "CPF": "09479499762",
    "PRESTADORES": "IZABELA FERREIRA COSTA",
    "Contato": 27999860356,
    "Contato 2": 27999564334,
    "E-mail": "belacosta8@hotmail.com",
    "CEP": 29060300,
    "Endereco ": "Rua Jose Neves Cypreste",
    "Numero": 489,
    "Bairro": "Jardim da Penha"
  },
  {
    "ID": 44,
    "CPF": "01548333719",
    "PRESTADORES": "JAIME BREDA",
    "Contato": 27996509023,
    "E-mail": "jaime07breda@gmail.com",
    "CEP": 29066370,
    "Endereco ": "Avenida Adalberto Simao Nader",
    "Numero": 565,
    "Complemento": "565",
    "Bairro": "Mata da Praia"
  },
  {
    "ID": 45,
    "CPF": "85372242787",
    "PRESTADORES": "JANE HAHNL",
    "Contato": 27998040843,
    "E-mail": "jane.hahnl@terra.com.br",
    "CEP": 29056922,
    "Endereco ": "Avenida Nossa Senhora da Penha",
    "Numero": 595,
    "Complemento": "tifanny center",
    "Bairro": "Santa Lucia, Vit\u00F3ria"
  },
  {
    "ID": 46,
    "CPF": "06619375502",
    "PRESTADORES": "JASON MATHIAS PIMENTA QUEIROZ",
    "Contato": 27992040230,
    "E-mail": "mathias_piimenta@hotmail.com",
    "CEP": 29146200,
    "Endereco ": "Avenida Expedito Garcia",
    "Numero": 68,
    "Complemento": "sala 103",
    "Bairro": "Campo Grande"
  },
  {
    "ID": 47,
    "PRESTADORES": "JHOAN LUCAS BAUER",
    "Contato": 27998289616,
    "E-mail": "drlucasbalen@gmail.com",
    "CEP": 29045160,
    "Endereco ": "Rua vinte",
    "Numero": 101,
    "Bairro": "Santa monica, vila velha"
  },
  {
    "ID": 48,
    "CPF": "84348216720",
    "PRESTADORES": "JOANA DARC GRILLO",
    "Contato": 27988273258,
    "E-mail": "grillojoana@gmail.com",
    "CEP": 29050545,
    "Endereco ": "Rua Jose Alexandre Buaiz",
    "Numero": 190,
    "Bairro": "Enseada do Sua"
  },
  {
    "ID": 49,
    "CPF": "49020498649",
    "PRESTADORES": "JOSUE BARCELOS VIANA",
    "Contato": 27988881506,
    "E-mail": "josue.odontologia@gmail.com",
    "CEP": 29056210,
    "Endereco ": "Rua das Palmeiras",
    "Numero": 795,
    "Bairro": "Santa Lucia"
  },
  {
    "ID": 50,
    "CPF": "13652105702",
    "PRESTADORES": "JULIANA DA CUNHA RANGEL",
    "Contato": 27999698772,
    "E-mail": "ortojulianarangel@gmail.com",
    "CEP": 29050545,
    "Endereco ": "Rua Jose Alexandre Buaiz",
    "Numero": 190,
    "Bairro": "Enseada do Sua"
  },
  {
    "ID": 51,
    "PRESTADORES": "JULIANA DALCOL",
    "Contato": 27999299029,
    "E-mail": "julianadalcol@hotmail.com",
    "CEP": 29066310
  },
  {
    "ID": 52,
    "CPF": "09750039769",
    "PRESTADORES": "KLEITON NUNES BORGHI",
    "Contato": 27997457657,
    "E-mail": "consultoriodr.kleiton@hotmail.com",
    "CEP": 29780000,
    "Endereco ": "Galeria Olinto Feliciano Zanotelli",
    "Numero": 63,
    "Complemento": "loja 1",
    "Bairro": "centro "
  },
  {
    "ID": 53,
    "CPF": "14797948728",
    "PRESTADORES": "LARA BRUSCHI",
    "Contato": 27992355554,
    "Contato 2": 27995221892,
    "E-mail": "laracbruschi@gmail.com",
    "CEP": 29090100,
    "Endereco ": "Rua Gelu Vervloet dos Santos",
    "Numero": 590,
    "Complemento": "sala 709",
    "Bairro": "Jardim Camburi"
  },
  {
    "ID": 54,
    "CPF": "09235807786",
    "PRESTADORES": "LAYSSA BATISTA DEGLI ESPOSTI",
    "Contato": 27988521144,
    "E-mail": "layssa28@yahoo.com.br",
    "CEP": 29050911,
    "Endereco ": "Avenida Americo Buaiz",
    "Numero": 501,
    "Complemento": "sala 201/203. Torre Leste. Ed. Victoria Office Tower",
    "Bairro": "Enseada Do Sua"
  },
  {
    "ID": 56,
    "CPF": "11738638774",
    "PRESTADORES": "LEANDRO FIGUEIREDO PEREIRA",
    "Contato": 27996199593,
    "E-mail": "Leandrofigueiredo.p@hotmail.com",
    "CEP": 29101575,
    "Endereco ": "Avenida Fortaleza",
    "Numero": 411,
    "Bairro": "Itapua, vila velha"
  },
  {
    "ID": 57,
    "CPF": "13470014760",
    "PRESTADORES": "LILIANA DARIVA BELISARIO",
    "Contato": 27998700212,
    "E-mail": "lilianabelisario@gmail.com",
    "CEP": 29102150,
    "Endereco ": "Rua Jose Felix Cheim",
    "Numero": 13,
    "Bairro": "Praia de Itaparica - Vila Velha"
  },
  {
    "ID": 58,
    "CPF": "08938859754",
    "PRESTADORES": "LOREN SOSSAI REGIANI",
    "Contato": 27998310529,
    "E-mail": "odontoloren@hotmail.com",
    "CEP": 29146201,
    "Endereco ": "Avenida Expedito Garcia",
    "Numero": 123,
    "Complemento": "sala 102",
    "Bairro": "Campo Grande"
  },
  {
    "ID": 59,
    "CPF": 14759788719,
    "PRESTADORES": "LORENA MORAES",
    "Contato": 27997989986,
    "E-mail": "lorenamoraes.gsm@gmail.com",
    "CEP": 29090740,
    "Endereco ": "Rua Maria Auxiliadora Gomes Salomao",
    "Numero": 116,
    "Complemento": "Ed. Solaris, sala 7"
  },
  {
    "ID": 60,
    "CPF": "09311898619",
    "CNPJ": "21035922000104",
    "PRESTADORES": "LORRAYNE GOMES TEODORO VIEIRA",
    "Contato": 27981471331,
    "E-mail": "ortodenteclinica@gmail.com",
    "CEP": 29165130,
    "Endereco ": "Avenida Central",
    "Numero": 834,
    "Bairro": "Parque Residencial Laranjeiras"
  },
  {
    "ID": 61,
    "CPF": "07396676703",
    "PRESTADORES": "MARCELA ARRABAL",
    "Contato": 27996046850,
    "E-mail": "marcela.arrabal@hotmail.com",
    "CEP": 29050470,
    "Endereco ": "Rua Taciano Abaurre",
    "Numero": 225,
    "Complemento": "3 andar - sala 306",
    "Bairro": "Enseada do Sua"
  },
  {
    "ID": 62,
    "CPF": "10758365730",
    "PRESTADORES": "MARCELLE PEREIRA MONTEIRO",
    "Contato": 27999837218,
    "E-mail": "odonto03mpm@hotmail.com",
    "CEP": 29092270,
    "Endereco ": "Rua Jose Alexandre Buaiz",
    "Numero": 190,
    "Complemento": "sala 511, Edificio Master Tower - Em frente o Tribunal de Contas do Estado.",
    "Bairro": "Enseada do Sua, Vitoria"
  },
  {
    "ID": 63,
    "CPF": "03200003707",
    "PRESTADORES": "MARCELO LIEVORE BRANDAO",
    "Contato": 27999744680,
    "E-mail": "marcelolievore@hotmail.com",
    "CEP": 29055912,
    "Endereco ": "Avenida Nossa Sra. da Penha",
    "Numero": 570,
    "Complemento": "Clinica - Brandao & Daher",
    "Bairro": "PRAIA DO CANTO "
  },
  {
    "ID": 64,
    "CPF": "63597039634",
    "PRESTADORES": "MARCELO SCHULTZ MORAES",
    "Contato": 22999748452,
    "E-mail": "ortoschultz@outlook.com",
    "CEP": 28010170,
    "Endereco ": "Rua Vinte e Um de Abril",
    "Numero": 272,
    "Complemento": "sala 513",
    "Bairro": "Centro"
  },
  {
    "ID": 65,
    "CPF": "07403345738",
    "PRESTADORES": "MARCO AURELIO FONTAN",
    "Contato": 27999810168,
    "E-mail": "marco.fontan@hotmail.com",
    "CEP": 29370000,
    "Endereco ": "Avenida Jose Grilo",
    "Numero": 648,
    "Complemento": "sala 305",
    "Bairro": "Centro"
  },
  {
    "ID": 66,
    "CPF": "11190580748",
    "PRESTADORES": "MARCUS THADEU NETO RIBEIRO",
    "Contato": 27998751630,
    "E-mail": "drmarcusthadeu@gmail.com",
    "CEP": 29165460,
    "Endereco ": "Rua Miguel angelo",
    "Numero": 182,
    "Complemento": "primeiro andar sala 2",
    "Bairro": "Parque Residencial Laranjeiras"
  },
  {
    "ID": 67,
    "CPF": "79695205704",
    "PRESTADORES": "MARGARETH DOMINGUES COACHMAN",
    "Contato": 27999246363,
    "Contato 2": 27981161162,
    "E-mail": "margaret.coachman@uol.com.br",
    "CEP": 29055130,
    "Endereco ": "Avenida Nossa Senhora da Penha",
    "Numero": 714,
    "Complemento": "apto 805",
    "Bairro": "Praia do Canto"
  },
  {
    "ID": 68,
    "CPF": "01049535278",
    "PRESTADORES": "MARIA BEATRIZ SCHOTT",
    "Contato": 69984589205,
    "E-mail": "odontombeatriz@gmail.com",
    "CEP": 29106595,
    "Endereco ": "Rua Cristovao Colombo",
    "Numero": 834,
    "Complemento": "loja 06, sala 836",
    "Bairro": "Cristovao Colombo, Vila Velha"
  },
  {
    "ID": 69,
    "CPF": "75143232791",
    "PRESTADORES": "MARIA DA PENHA BORTOLIN MULLER",
    "Contato": 27997990127,
    "E-mail": "penhabortolin@gotmail",
    "CEP": 29055940,
    "Endereco ": "Avenida Nossa Senhora da Penha",
    "Numero": 570,
    "Complemento": "apto 1104",
    "Bairro": "Praia do Canto"
  },
  {
    "ID": 70,
    "CPF": "15216389776",
    "PRESTADORES": "MARIANA CARREIRO ZANI",
    "Contato": 27998576798,
    "Contato 2": 27998635805,
    "E-mail": "marianacarreiro4@hotmail.com",
    "CEP": 29101340,
    "Endereco ": "Rua Maranhao",
    "Numero": 575,
    "Complemento": "sala 113, Torre Sul",
    "Bairro": "Praia da Costa"
  },
  {
    "ID": 71,
    "CPF": "15953151799",
    "PRESTADORES": "MARIANA FARIA MOREIRA",
    "Contato": 27998026369,
    "E-mail": "mariana_fmoreira@hotmail.com",
    "CEP": 29066310,
    "Endereco ": "Avenida Adalberto Simao Nader",
    "Numero": 565,
    "Bairro": "Mata da Praia"
  },
  {
    "ID": 72,
    "PRESTADORES": "MARILHA GUEDES DIAS",
    "Contato": 27999646339,
    "E-mail": "Mariliaguedesdias24@gmail.com",
    "CEP": 29090100,
    "Endereco ": "Rua Gelu Vervloet dos Santos",
    "Numero": 590,
    "Complemento": "Ed. Norte e sul tower, sala 1204",
    "Bairro": "Jardim Camburi, vitoria"
  },
  {
    "ID": 73,
    "CPF": "11118508793",
    "PRESTADORES": "MATEUS SANTOS FERNANDES",
    "Contato": 27999681400,
    "E-mail": "mateustisco@gmail.com",
    "CEP": 29165680,
    "Endereco ": "Avenida Eldes Scherrer Souza",
    "Numero": 975,
    "Complemento": "ed. Ative, 10 andar, sala 1013."
  },
  {
    "ID": 74,
    "CNPJ": "48518046000123",
    "PRESTADORES": "MAYARA GOMES DE OLIVEIRA",
    "Contato": 27999672122,
    "CEP": 29102203,
    "Endereco ": "Rua Dylio Penedo",
    "Numero": 8,
    "Bairro": "Praia de Itaparica, Vila Velha"
  },
  {
    "ID": 75,
    "CPF": "05492673793",
    "PRESTADORES": "MAYKO DIAS",
    "Contato": 27992386490,
    "Contato 2": 27996476297,
    "E-mail": "maykobr@hotmail.com",
    "CEP": 29055300,
    "Endereco ": "Rua Doutor Eurico de Aguiar",
    "Numero": 246,
    "Bairro": "Praia do Canto"
  },
  {
    "ID": 79,
    "CPF": "08798622625",
    "PRESTADORES": "MELINA LINHARES FRIZZERA",
    "Contato": 27998093738,
    "E-mail": "melina_frizzera@hotmail.com",
    "CEP": 29060050,
    "Endereco ": "Rua Odette de Oliveira Lacourt",
    "Numero": 723,
    "Complemento": "ap 304 Ed W nico",
    "Bairro": "jardim da Penha"
  },
  {
    "ID": 76,
    "CPF": "07286145703",
    "PRESTADORES": "MICHELLE HENRIQUES VAZ DE MELO BRUGNI",
    "Contato": 27999605730,
    "E-mail": "milvazdemelo@hotmail.com",
    "CEP": 29092110,
    "Endereco ": "Rua Carlos Lindenberg",
    "Numero": 40,
    "Complemento": "Ed San Gennaro, sala 302",
    "Bairro": "Jardim Camburi, Vit\u00F3ria"
  },
  {
    "ID": 77,
    "PRESTADORES": "MICKAEL BOECHAT",
    "CEP": 30710340,
    "Endereco ": "Rua Sabinopolis",
    "Numero": 158,
    "Complemento": "202",
    "Bairro": "Carlos Prates"
  },
  {
    "ID": 78,
    "CPF": "14366292769",
    "PRESTADORES": "MILENA DE PAULA SANTOS",
    "Contato": 27999402508,
    "E-mail": "dramilenasantos@outlook.com",
    "CEP": 29056210,
    "Endereco ": "Rua Arlindo da Mota",
    "Numero": 721,
    "Complemento": "Santorini Offices. Santa lucia - Sala 1201 (alugo sala da Renata Covre)",
    "Bairro": "Santa Lucia, Vitoria"
  },
  {
    "ID": 80,
    "CPF": "07217428742",
    "PRESTADORES": "MIRIAM GOTTARDI",
    "Contato": 27999104559,
    "E-mail": "mi.gottardi@gmail.com",
    "CEP": 29050918,
    "Endereco ": "Rua Jose Alexandre Buaiz",
    "Numero": 190,
    "Complemento": "sala 1206",
    "Bairro": "Enseada de Sua"
  },
  {
    "ID": 81,
    "CPF": "14312472785",
    "PRESTADORES": "MURILO TOSI STOCCO",
    "Contato": 27997391868,
    "E-mail": "murilo.stocco@hotmail.com",
    "CEP": 29173675,
    "Endereco ": "Rua Dilson Bitencourt Feu",
    "Numero": 18,
    "Bairro": "Praia de Capuba"
  },
  {
    "ID": 82,
    "CPF": "86261452768",
    "PRESTADORES": "NARA CHEQUER",
    "Contato": 27996867280,
    "E-mail": "nara.ac@terra.com.br",
    "CEP": 29055131,
    "Endereco ": "Avenida Nossa Senhora da Penha",
    "Numero": 570,
    "Complemento": "sala 512"
  },
  {
    "ID": 83,
    "CPF": "10964032775",
    "PRESTADORES": "NARALICE DE AQUINO",
    "Contato": 27992445547,
    "Contato 2": 31989243369,
    "E-mail": "coordenacaoodontosolidaris@gmail.com",
    "CEP": 29100401,
    "Endereco ": "Avenida JerOnimo Monteiro",
    "Numero": 1527,
    "Bairro": "Centro de Vila Velha"
  },
  {
    "ID": 84,
    "CPF": "11823117767",
    "PRESTADORES": "NATHALIA FINCK",
    "Contato": 27998029410,
    "E-mail": "nathaliafinck@gmail.com",
    "CEP": 29100902,
    "Endereco ": "Avenida JerOnimo Monteiro",
    "Numero": 1690,
    "Bairro": "Centro de Vila Velha"
  },
  {
    "ID": 85,
    "CPF": "04590773767",
    "PRESTADORES": "NICOLAS YANN RODRIGUES MATEUS",
    "Contato": 27999428833,
    "Contato 2": 27988026477,
    "E-mail": "nicolasyann@yahoo.com.br",
    "CEP": 29101441,
    "Endereco ": "Avenida Afonso Pena",
    "Numero": 235,
    "Bairro": "Praia da Costa"
  },
  {
    "ID": 86,
    "CPF": "03143530707",
    "PRESTADORES": "NIRLEY APARECIDA DOS SANTOS VIEIRA",
    "Contato": 27998645880,
    "E-mail": "nirleysantosvieira@gmail.com",
    "CEP": 29136013,
    "Endereco ": "Rua Santa Helena",
    "Numero": 103,
    "Bairro": "Vila Bethania- Viana"
  },
  {
    "ID": 87,
    "CPF": "04592163761",
    "PRESTADORES": "PATRICIA ROCCON BIANCHI",
    "Contato": 27999257707,
    "E-mail": "patricia.rbianchi@yahoo.com.br",
    "CEP": 29050565,
    "Endereco ": "Rua Prof. Almeida Cousin",
    "Numero": 125,
    "Complemento": "Ed. Enseada Trade Center",
    "Bairro": "Enseada do Sua"
  },
  {
    "ID": 89,
    "CPF": "07079585716",
    "PRESTADORES": "PAULA STEFANO SALIBA PEREIRA",
    "Contato": 27998191554,
    "E-mail": "paulasaliba22@gmail.com",
    "CEP": 29090100,
    "Endereco ": "Rua Gelu Vervloet dos Santos",
    "Numero": 500,
    "Complemento": "608",
    "Bairro": "Jardim Camburi"
  },
  {
    "ID": 90,
    "CPF": "10350642788",
    "PRESTADORES": "PHALOMA SILVA PEREIRA",
    "Contato": 27995763498,
    "Contato 2": 27992989638,
    "E-mail": "ihcofodontologia@gmail.com",
    "CEP": 29066310,
    "Endereco ": "Avenida Adalberto Simao Nader",
    "Numero": 565,
    "Bairro": "Mata da Praia"
  },
  {
    "ID": 91,
    "CPF": 14756717764,
    "PRESTADORES": "PILAR ARPINI MENDONCA",
    "Contato": 27999280336,
    "E-mail": "pilararpini@gmail.com",
    "CEP": 29090720,
    "Endereco ": "Avenida Judith Leao Castello Ribeiro",
    "Numero": 645,
    "Bairro": "Jardim Camburi"
  },
  {
    "ID": 92,
    "CPF": "08454553703",
    "PRESTADORES": "PRISCILA PINHEIRO DAMIAO DE OLIVEIRA",
    "Contato": 27997772424,
    "E-mail": "damiaoodonto@gmail.com",
    "CEP": 29066040,
    "Endereco ": "Avenida Carlos Gomes de Sa",
    "Numero": 730,
    "Complemento": "sala 204",
    "Bairro": "Mata da Praia"
  },
  {
    "ID": 93,
    "CPF": "09579421765",
    "PRESTADORES": "RAFAELLA  DE OLIVEIRA ROBSON MATTAR",
    "Contato": 27999336839,
    "E-mail": "rafarobson@yahoo.com.br",
    "CEP": 29165680,
    "Endereco ": "Avenida eudes scherrer de souza",
    "Numero": 1025,
    "Complemento": "sala 912/913 - Centro Empresarial da Serra"
  },
  {
    "ID": 94,
    "CPF": "00512114757",
    "PRESTADORES": "RENATO DE AGUIAR RIBEIRO",
    "Contato": 27998778514,
    "E-mail": "odontointegrada.ra@gmail.com",
    "CEP": 29055280,
    "Endereco ": "Rua Doutor Eurico de Aguiar",
    "Numero": 130,
    "Bairro": "Praia do Canto"
  },
  {
    "ID": 95,
    "CPF": "10055245722",
    "PRESTADORES": "ROBSON SPINASSE",
    "Contato": 27998480373,
    "E-mail": "robsonspinasse@hotmail.com",
    "CEP": 29900300,
    "Endereco ": "Praca Nestor Gomes",
    "Numero": 152,
    "Bairro": "Centro"
  },
  {
    "ID": 96,
    "CPF": "07870334723",
    "PRESTADORES": "RODRIGO COSTA PISSINATTI",
    "Contato": 27992590929,
    "E-mail": "rodrigopissinatti06@gmail.com",
    "CEP": 29101340,
    "Endereco ": "Rua Maranhao",
    "Numero": 575,
    "Complemento": "sala 101 - Ed Torre Sul"
  },
  {
    "ID": 97,
    "CPF": "79798535715",
    "PRESTADORES": "RODRIGO GIUBERTI",
    "Contato": 27997856606,
    "E-mail": "giubertiodontologia@gmail.com",
    "CEP": 29102020,
    "Endereco ": "Rodovia do Sol",
    "Numero": 2,
    "Bairro": "Praia de Itaparica"
  },
  {
    "ID": 98,
    "CPF": "04496915782",
    "PRESTADORES": "RODRIGO PERES MORGADO",
    "Contato": 73999971511,
    "E-mail": "prodente5833@gmail.com",
    "CEP": 45990301,
    "Endereco ": "Rua do Haiti",
    "Numero": 44,
    "Bairro": "Bela Vista"
  },
  {
    "ID": 99,
    "CPF": "11715992776",
    "PRESTADORES": "RODRIGO SCALFONI GAVINA",
    "Contato": 27999862705,
    "E-mail": "rsgavina@gmail.com",
    "CEP": 29066370,
    "Endereco ": "Avenida Adalberto Simao Nader",
    "Numero": 565,
    "Complemento": "565",
    "Bairro": "Mata da Praia"
  },
  {
    "ID": 100,
    "CPF": "07319227789",
    "CNPJ": "14242673000162",
    "PRESTADORES": "ROGERIO CESCONETO",
    "Contato": 27999849938,
    "E-mail": "rcesconeto@hotmail.com",
    "CEP": 29066310,
    "Endereco ": "Avenida Adalberto Simao Nader",
    "Numero": 152,
    "Bairro": "Mata da Praia"
  },
  {
    "ID": 101,
    "CPF": "03941999796",
    "PRESTADORES": "ROGERIO DEGLI ESPOSTI BORGES",
    "Contato": 27997131180,
    "E-mail": "rogerioesposti@yahoo.com.br",
    "CEP": 29165680,
    "Endereco ": "Avenida eldes scherrer souza",
    "Numero": 975,
    "Complemento": "SALA 1013 ED. CENTRO EMPRASARIAL ATIVE",
    "Bairro": "Serra"
  },
  {
    "ID": 102,
    "CPF": "11144733758",
    "PRESTADORES": "ROMULO POSSATTO LUCAS",
    "Contato": 27995149653,
    "CEP": 29171454,
    "Endereco ": "Rua Albatroz",
    "Numero": 42,
    "Bairro": "Serra Dourada 3, Serra"
  },
  {
    "ID": 103,
    "CPF": "67720340663",
    "PRESTADORES": "RONALD CORReA FAVERO",
    "Contato": 27981449730,
    "E-mail": "ronaldfavero@hotmail.com",
    "CEP": 29200430,
    "Endereco ": "Avenida Davino Mattos",
    "Numero": 55,
    "Complemento": "103",
    "Bairro": "Centro"
  },
  {
    "ID": 104,
    "CPF": "11023652706",
    "PRESTADORES": "RONY SCARDUA GARCIA",
    "Contato": 27999248688,
    "E-mail": "dr.ronyscarduagarcia@gmail.com",
    "CEP": 29163331,
    "Endereco ": "Avenida Brasil",
    "Numero": 1140,
    "Bairro": "Novo Horizonte, Serra-ES"
  },
  {
    "ID": 105,
    "CPF": "12431219712",
    "PRESTADORES": "RUBIA CAUS PEREIRA ALVES",
    "Contato": 27988154325,
    "E-mail": "rubiacaus@gmail.com",
    "CEP": 29100901,
    "Endereco ": "Avenida Jeronimo Monteiro",
    "Numero": 1690,
    "Complemento": "sala 64-A",
    "Bairro": "Centro, VV"
  },
  {
    "ID": 106,
    "CPF": "98225650700",
    "PRESTADORES": "SINGRID MELO SALIBA",
    "Contato": 27998144858,
    "E-mail": "odontoclinica@hotmail.com",
    "CEP": 29055270,
    "Endereco ": "Rua Eugenio Netto",
    "Numero": 488,
    "Complemento": "sala 1007",
    "Bairro": "Praia do Canto"
  },
  {
    "ID": 107,
    "CPF": "16308864757",
    "PRESTADORES": "STEFANI KELLY PEREIRA AGUIAR",
    "Contato": 27992290644,
    "E-mail": "stefaniaguiar@hotmail.com",
    "CEP": 29066370,
    "Endereco ": "Avenida Adalberto Simao Nader",
    "Numero": 565,
    "Bairro": "Mata da Praia"
  },
  {
    "ID": 108,
    "CPF": "07387414777",
    "PRESTADORES": "THIAGO BATISTA",
    "Contato": 27999827745,
    "E-mail": "odontologiadegliesposti@gmail.com",
    "CEP": 29050911,
    "Endereco ": "Avenida Americo Buaiz",
    "Numero": 501,
    "Complemento": "torre leste sala 203",
    "Bairro": "Enseada do Sua"
  },
  {
    "ID": 109,
    "CPF": "08079059764",
    "PRESTADORES": "VANESSA NASCIMENTO LOUREIRO",
    "Contato": 27999410778,
    "E-mail": "vnloureiro@hotmail.com",
    "CEP": 29176080,
    "Endereco ": "Rua ROmulo Castello",
    "Numero": 57,
    "Bairro": "Serra Centro"
  },
  {
    "ID": 110,
    "CPF": "14026024725",
    "PRESTADORES": "VIKTOR ARNALDO",
    "Contato": 27999405266,
    "E-mail": "viktorangeli@gmail.com",
    "CEP": 29066310,
    "Endereco ": "Rua Rio Grande",
    "Numero": 15,
    "Bairro": "Eldorado"
  },
  {
    "ID": 111,
    "CPF": "10375705619",
    "PRESTADORES": "VINICIUS HUBNER FLORINDO",
    "Contato": 27999592535,
    "E-mail": "dr.viniciushubner@gmail.com",
    "CEP": 29101094,
    "Endereco ": "Rua Hinacio Higino",
    "Numero": 1050,
    "Complemento": "Edificio Centro Empresarial Shopping Praia da Costa Torre Leste. Sala 901",
    "Bairro": "Praia da Costa"
  },
  {
    "ID": 112,
    "CPF": "09804495708",
    "PRESTADORES": "VITOR AONI",
    "Contato": 27998438456,
    "Contato 2": 27998989395,
    "E-mail": "dr.vitoraoni@gmail.com",
    "CEP": 29100021,
    "Endereco ": "Avenida Henrique Moscoso",
    "Numero": 1019,
    "Bairro": "Centro de Vila Velha"
  },
  {
    "ID": 113,
    "CPF": "12180448708",
    "PRESTADORES": "VITOR FREITAS MENEZES",
    "Contato": 27981368812,
    "E-mail": "vitormenezes88@hotmail.com",
    "CEP": 29106595,
    "Endereco ": "Rua Cristovao Colombo",
    "Numero": 834,
    "Complemento": "loja 06",
    "Bairro": "Cristovao Colombo - Vila Velha"
  },
  {
    "ID": 114,
    "CPF": "00789552701",
    "PRESTADORES": "WAGNER PIZZOL",
    "Contato": 27999139963,
    "E-mail": "consultorio.wagnerpizzol@gmail.com",
    "CEP": 29193045,
    "Endereco ": "Rua Giovani Modenesi",
    "Numero": 12,
    "Bairro": "Jequitiba"
  },
  {
    "ID": 115,
    "CPF": "07356081725",
    "PRESTADORES": "WILLIAM CESAR CASTELAN PANETO",
    "Contato": 28999111150,
    "E-mail": "panetow50@hotmail.com",
    "CEP": 29360000,
    "Endereco ": "Rua Bernardino Monteiro ",
    "Numero": 50,
    "Complemento": "emilio nemer center sala 05",
    "Bairro": "centro"
  },
  {
    "ID": 116,
    "CNPJ": "14242673000162",
    "PRESTADORES": "(CLINICA) CERAMIC"
  },
  {
    "ID": 117,
    "CNPJ": "48699539000107",
    "PRESTADORES": "(CLINICA) DAVILA ODONTOLOGIA AVANCADA LTDA",
    "Contato": 27998635805,
    "E-mail": "davila.odonto2@gmail.com",
    "CEP": 29101340,
    "Endereco ": "Rua Maranhao",
    "Numero": 575,
    "Complemento": "Torre Sul, sala 113/primeiro andar",
    "Bairro": "Praia da Costa - Vila Velha"
  },
  {
    "ID": 118,
    "PRESTADORES": "(CLINICA) FAMA CURSOS DE FORMACAO PROFISSIONAL LTDA",
    "CEP": 29066370
  },
  {
    "ID": 119,
    "PRESTADORES": "(CLINICA) GAMA ODONTOLOGIA LTDA",
    "Contato": 27999672122,
    "E-mail": "adm.gamaodontologia@gmail.com",
    "CEP": 29102203,
    "Endereco ": "Rua Dylio Penedo",
    "Numero": 8,
    "Bairro": "Praia de Itaparica, Vila Velha"
  },
  {
    "ID": 120,
    "CNPJ": "36893181000170",
    "PRESTADORES": "(CLINICA) IHCOF - INSTITUTO DE HARM. E CIRUR.",
    "Contato": 27995763498,
    "E-mail": "ihcofodontologia@gmail.com"
  },
  {
    "ID": 121,
    "PRESTADORES": "(CLINICA) INOVI",
    "CEP": 29066370,
    "Endereco ": "Avenida Adalberto Sim\u00E3o Nader",
    "Numero": 565,
    "Bairro": "Mata da Praia, vitoria"
  },
  {
    "ID": 122,
    "CNPJ": "10260145000185",
    "PRESTADORES": "(CLINICA) INSTITUTO RIVA"
  },
  {
    "ID": 123,
    "PRESTADORES": "(CLINICA) INSTRUMENTADORA FF ODONTOLOGIA"
  },
  {
    "ID": 124,
    "CPF": "08338330736",
    "PRESTADORES": "(CLINICA) MAGIC DENT",
    "Contato": 27992647604,
    "CEP": 29050912,
    "Endereco ": "Avenida Nossa Senhora dos Navegantes",
    "Numero": 675,
    "Bairro": "Enseada do Sua"
  },
  {
    "ID": 125,
    "PRESTADORES": "(CLINICA) MAIS ODONTOLOGIA INTEGRADA"
  },
  {
    "ID": 126,
    "CNPJ": "21035922000104",
    "PRESTADORES": "(CLINICA) ORTODENTE CLINICA ODONTOLOGICA LTDA",
    "Contato": 27981471331,
    "E-mail": "ortodenteclinica@gmail.com",
    "CEP": 29165130,
    "Endereco ": "Avenida Central",
    "Numero": 834,
    "Bairro": "Parque Residencial Laranjeiras"
  },
  {
    "ID": 127,
    "PRESTADORES": "(CLINICA) PRODENTE"
  },
  {
    "ID": 128,
    "CNPJ": "17490149000107",
    "PRESTADORES": "(CLINICA) VELLOSO ODONTOLOGIA",
    "Contato": 27997896216,
    "E-mail": "contato@vellosoodonto.com",
    "CEP": 29090100,
    "Endereco ": "Rua Gelu Vervloet dos Santos",
    "Numero": 500,
    "Complemento": "sala 1403",
    "Bairro": "Jardim Camburi, Vitoria"
  }
]
